<?xml version="1.0" standalone="no" ?>
<mission>
	<desc>
		Iver compass calibration mission
	</desc>
	<global>
		<location lat="-29.9385" lon="159.1223" />
		<turn_radius m="5" />
		<drop_distance m="4" />
		<drop_angle deg="40" />
		<mission_timeout t = "1"/>
		<!-- Mission timeout not implemented. To have the same drop distance in the corners use drop_angle [rad] = drop_distance / turn_radius -->
	</global>
	<primitive>
		<goto>
			<position x="-2543.62099474" y="928.9464653" z="5.0"/>
			<heading deg="-174.061091487" />
			<timeout t="3000" />
			<velocity x="0.75" />
			<depth mode = "depth" />
		</goto>
	</primitive>
	<primitive>
		<goto>
			<position x="-2543.62099474" y="928.9464653" z="2.0"/>
			<heading deg="-174.061091487" />
			<timeout t="3000" />
			<velocity x="0.75" />
			<depth mode = "altitude" />
		</goto>
	</primitive>
	<primitive>
		<goto>
			<position x="-2543.62099474" y="928.9464653" z="2.0"/>
			<heading deg="-174.061091487" />
			<timeout t="3000" />
			<velocity x="0.75" />
			<depth mode = "altitude" />
			<command device="camera" onoff="start"/>
		</goto>
	</primitive>
	<primitive>
		<goto>
			<position x="-4036.16425725" y="773.682668336" z="2.0"/>
			<heading deg="95.9388939312" />
			<timeout t="3000" />
			<velocity x="0.75" />
			<depth mode = "altitude" />
		</goto>
	</primitive>
	<primitive>
		<goto>
			<position x="-4046.51515156" y="873.185553578" z="2.0"/>
			<heading deg="5.93890870679" />
			<timeout t="3000" />
			<velocity x="0.75" />
			<depth mode = "altitude" />
		</goto>
	</primitive>
	<primitive>
		<goto>
			<position x="-2553.97193991" y="1028.44935036" z="2.0"/>
			<heading deg="95.9389215724" />
			<timeout t="3000" />
			<velocity x="0.75" />
			<depth mode = "altitude" />
		</goto>
	</primitive>
	<primitive>
		<goto>
			<position x="-2564.3228815" y="1127.95222355" z="2.0"/>
			<heading deg="-174.061091504" />
			<timeout t="3000" />
			<velocity x="0.75" />
			<depth mode = "altitude" />
		</goto>
	</primitive>
	<primitive>
		<goto>
			<position x="-4056.86605384" y="972.688436419" z="2.0"/>
			<heading deg="-174.061091504" />
			<timeout t="3000" />
			<velocity x="0.75" />
			<depth mode = "altitude" />
		</goto>
	</primitive>
	<primitive>
		<goto>
			<position x="-4056.86605384" y="972.688436419" z="0.0"/>
			<heading deg="-174.061091504" />
			<timeout t="3000" />
			<velocity x="0.75" />
			<depth mode = "depth" />
			<command device="camera" onoff="stop"/>
		</goto>
	</primitive>
</mission>
