<?xml version="1.0" standalone="no" ?>
<mission>
	<desc>
		Iver compass calibration mission
	</desc>
	<global>
		<location lat="-29.4339" lon="159.0721" />
		<turn_radius m="5" />
		<drop_distance m="4" />
		<drop_angle deg="40" />
		<mission_timeout t = "1"/>
		<!-- Mission timeout not implemented. To have the same drop distance in the corners use drop_angle [rad] = drop_distance / turn_radius -->
	</global>
	<primitive>
		<goto>
			<position x="606.655957306" y="-783.896376541" z="0.0"/>
			<heading deg="120.035432368" />
			<timeout t="3000" />
			<velocity x="0.75" />
			<depth mode = "depth" />
		</goto>
	</primitive>
	<primitive>
		<goto>
			<position x="606.655957306" y="-783.896376541" z="2.0"/>
			<heading deg="120.035432368" />
			<timeout t="3000" />
			<velocity x="0.75" />
			<depth mode = "altitude" />
		</goto>
	</primitive>
	<primitive>
		<goto>
			<position x="606.655957306" y="-783.896376541" z="2.0"/>
			<heading deg="120.035432368" />
			<timeout t="3000" />
			<velocity x="0.75" />
			<depth mode = "altitude" />
			<command device="camera" onoff="start"/>
		</goto>
	</primitive>
	<primitive>
		<goto>
			<position x="-144.447199587" y="515.196477396" z="2.0"/>
			<heading deg="-149.964569031" />
			<timeout t="3000" />
			<velocity x="0.75" />
			<depth mode = "altitude" />
		</goto>
	</primitive>
	<primitive>
		<goto>
			<position x="-231.053398693" y="465.122931311" z="2.0"/>
			<heading deg="-59.9645669242" />
			<timeout t="3000" />
			<velocity x="0.75" />
			<depth mode = "altitude" />
		</goto>
	</primitive>
	<primitive>
		<goto>
			<position x="520.049780407" y="-833.969923994" z="2.0"/>
			<heading deg="-149.964558913" />
			<timeout t="3000" />
			<velocity x="0.75" />
			<depth mode = "altitude" />
		</goto>
	</primitive>
	<primitive>
		<goto>
			<position x="468.086075694" y="-864.01405536" z="2.0"/>
			<heading deg="-149.964564449" />
			<timeout t="3000" />
			<velocity x="0.75" />
			<depth mode = "altitude" />
		</goto>
	</primitive>
	<primitive>
		<goto>
			<position x="433.443604056" y="-884.043472863" z="2.0"/>
			<heading deg="120.03543391" />
			<timeout t="3000" />
			<velocity x="0.75" />
			<depth mode = "altitude" />
		</goto>
	</primitive>
	<primitive>
		<goto>
			<position x="-317.659607557" y="415.049394999" z="2.0"/>
			<heading deg="120.03543391" />
			<timeout t="3000" />
			<velocity x="0.75" />
			<depth mode = "altitude" />
		</goto>
	</primitive>
	<primitive>
		<goto>
			<position x="-317.659607557" y="415.049394999" z="0.0"/>
			<heading deg="120.03543391" />
			<timeout t="3000" />
			<velocity x="0.75" />
			<depth mode = "depth" />
			<command device="camera" onoff="stop"/>
		</goto>
	</primitive>
</mission>
