<?xml version="1.0" standalone="no" ?>
<mission>
	<desc>
		Iver compass calibration mission
	</desc>
	<global>
		<location lat="-29.4339" lon="159.0721" />
		<turn_radius m="5" />
		<drop_distance m="4" />
		<drop_angle deg="40" />
		<mission_timeout t = "1"/>
		<!-- Mission timeout not implemented. To have the same drop distance in the corners use drop_angle [rad] = drop_distance / turn_radius -->
	</global>
	<primitive>
		<goto>
			<position x="-1387.77259395" y="-341.404151121" z="0.0"/>
			<heading deg="80.0354272929" />
			<timeout t="3000" />
			<velocity x="0.75" />
			<depth mode = "depth" />
		</goto>
	</primitive>
	<primitive>
		<goto>
			<position x="-1387.77259395" y="-341.404151121" z="2.0"/>
			<heading deg="80.0354272929" />
			<timeout t="3000" />
			<velocity x="0.75" />
			<depth mode = "altitude" />
		</goto>
	</primitive>
	<primitive>
		<goto>
			<position x="-1387.77259395" y="-341.404151121" z="2.0"/>
			<heading deg="80.0354272929" />
			<timeout t="3000" />
			<velocity x="0.75" />
			<depth mode = "altitude" />
			<command device="camera" onoff="start"/>
		</goto>
	</primitive>
	<primitive>
		<goto>
			<position x="-1128.11000633" y="1136.55886572" z="2.0"/>
			<heading deg="170.035418569" />
			<timeout t="3000" />
			<velocity x="0.75" />
			<depth mode = "altitude" />
		</goto>
	</primitive>
	<primitive>
		<goto>
			<position x="-1226.64086498" y="1153.86971875" z="2.0"/>
			<heading deg="-99.9645728235" />
			<timeout t="3000" />
			<velocity x="0.75" />
			<depth mode = "altitude" />
		</goto>
	</primitive>
	<primitive>
		<goto>
			<position x="-1486.30346039" y="-324.093324829" z="2.0"/>
			<heading deg="170.03543046" />
			<timeout t="3000" />
			<velocity x="0.75" />
			<depth mode = "altitude" />
		</goto>
	</primitive>
	<primitive>
		<goto>
			<position x="-1565.1281615" y="-310.244656772" z="2.0"/>
			<heading deg="170.035438677" />
			<timeout t="3000" />
			<velocity x="0.75" />
			<depth mode = "altitude" />
		</goto>
	</primitive>
	<primitive>
		<goto>
			<position x="-1584.83433789" y="-306.782492476" z="2.0"/>
			<heading deg="80.0354269785" />
			<timeout t="3000" />
			<velocity x="0.75" />
			<depth mode = "altitude" />
		</goto>
	</primitive>
	<primitive>
		<goto>
			<position x="-1325.17173439" y="1171.1805672" z="2.0"/>
			<heading deg="80.0354269785" />
			<timeout t="3000" />
			<velocity x="0.75" />
			<depth mode = "altitude" />
		</goto>
	</primitive>
	<primitive>
		<goto>
			<position x="-1325.17173439" y="1171.1805672" z="0.0"/>
			<heading deg="80.0354269785" />
			<timeout t="3000" />
			<velocity x="0.75" />
			<depth mode = "depth" />
			<command device="camera" onoff="stop"/>
		</goto>
	</primitive>
</mission>
